LPMatcher/LPMatcher.py
LPMatcher/__init__.py
LPMatcher/math_tools.py
LPMatcher-0.1.3.dist-info/LICENSE
LPMatcher-0.1.3.dist-info/METADATA
LPMatcher-0.1.3.dist-info/WHEEL
LPMatcher-0.1.3.dist-info/top_level.txt
LPMatcher-0.1.3.dist-info/RECORD
