Metadata-Version: 2.1
Name: LPMatcher
Version: 0.1.3
Summary: UNKNOWN
Home-page: UNKNOWN
Author: winter.yu
Author-email: winter741258@gmail.com
License: MIT
Platform: UNKNOWN
Classifier: License :: OSI Approved :: MIT License
Classifier: Operating System :: OS Independent
Classifier: Programming Language :: Python
Classifier: Programming Language :: Python :: 3
Classifier: Topic :: Software Development :: Libraries :: Python Modules
Requires-Python: >=3.6
License-File: LICENSE
Requires-Dist: opencv-python (>=4.5.4.60)
Requires-Dist: shapely
Requires-Dist: numpy
Requires-Dist: scipy
Requires-Dist: matplotlib
